wandbtocsv/__init__.py
wandbtocsv/_modidx.py
wandbtocsv/core.py
wandbtocsv-0.0.6.dist-info/LICENSE
wandbtocsv-0.0.6.dist-info/METADATA
wandbtocsv-0.0.6.dist-info/WHEEL
wandbtocsv-0.0.6.dist-info/entry_points.txt
wandbtocsv-0.0.6.dist-info/top_level.txt
wandbtocsv-0.0.6.dist-info/RECORD
