Metadata-Version: 2.1
Name: wandbtocsv
Version: 0.0.6
Summary: Export summary metrics and config from runs as a csv file from a project
Home-page: https://github.com/hamelsmu/wandbtocsv
Author: Hamel Husain
Author-email: hamel.husain@gmail.com
License: Apache Software License 2.0
Keywords: nbdev jupyter notebook python
Classifier: Development Status :: 4 - Beta
Classifier: Intended Audience :: Developers
Classifier: Natural Language :: English
Classifier: Programming Language :: Python :: 3.7
Classifier: Programming Language :: Python :: 3.8
Classifier: Programming Language :: Python :: 3.9
Classifier: Programming Language :: Python :: 3.10
Classifier: License :: OSI Approved :: Apache Software License
Requires-Python: >=3.7
License-File: LICENSE
Requires-Dist: fastcore
Requires-Dist: pandas
Requires-Dist: wandb
Requires-Dist: rich
Provides-Extra: dev
